X30/HBD2020.py
X30/__init__.py
X30-0.3.0.dist-info/METADATA
X30-0.3.0.dist-info/WHEEL
X30-0.3.0.dist-info/entry_points.txt
X30-0.3.0.dist-info/top_level.txt
X30-0.3.0.dist-info/RECORD
