Metadata-Version: 2.1
Name: X30
Version: 0.3.0
Summary: UNKNOWN
Home-page: https://scott870924.wixsite.com/yirutsai
Author: yirutsai
Author-email: b06502052@ntu.edu.tw
License: UNKNOWN
Download-URL: https://github.com/yirutsai/X30/archive/0.3.0.tar.gz
Platform: UNKNOWN
Requires-Dist: pygame
